MANIFEST.in
README.rst
bootstrap.py
buildout.cfg
setup+wine.py
setup.py
xbob/__init__.py
xbob.example.lda.egg-info/PKG-INFO
xbob.example.lda.egg-info/SOURCES.txt
xbob.example.lda.egg-info/dependency_links.txt
xbob.example.lda.egg-info/entry_points.txt
xbob.example.lda.egg-info/namespace_packages.txt
xbob.example.lda.egg-info/requires.txt
xbob.example.lda.egg-info/top_level.txt
xbob/example/__init__.py
xbob/example/lda/__init__.py
xbob/example/lda/iris.py
xbob/example/lda/wine.py