Metadata-Version: 1.1
Name: xbob.example.lda
Version: 1.0.3
Summary: (Fisher) Iris Flower LDA example
Home-page: http://pypi.python.org/pypi/xbob.example.lda
Author: Andre Anjos
Author-email: andre.anjos@idiap.ch
License: GPLv3
Platform: UNKNOWN
Classifier: Development Status :: 5 - Production/Stable
Classifier: Intended Audience :: Education
Classifier: License :: OSI Approved :: GNU General Public License v3 (GPLv3)
Classifier: Natural Language :: English
Classifier: Programming Language :: Python
Classifier: Topic :: Scientific/Engineering :: Artificial Intelligence
